pdc/__init__.cpython-310-x86_64-linux-gnu.so
pdc/container.cpython-310-x86_64-linux-gnu.so
pdc/main.cpython-310-x86_64-linux-gnu.so
pdc/object.cpython-310-x86_64-linux-gnu.so
pdc/query.cpython-310-x86_64-linux-gnu.so
pdc/region.cpython-310-x86_64-linux-gnu.so
pdcpy.libs/libhwloc-8a7ce5b6.so.5.7.5
pdcpy.libs/libltdl-448a9c0e.so.7
pdcpy.libs/libmercury-415401c0.so.2.2.0
pdcpy.libs/libmercury_util-d439ceb9.so.3.0.0
pdcpy.libs/libmpi-14335c9d.so.12.0.7
pdcpy.libs/libna-7b394883.so.3.0.0
pdcpy.libs/libnuma-428e8baf.so.1.0.0
pdcpy.libs/libopen-pal-4e447685.so.13.0.4
pdcpy.libs/libopen-rte-433d319d.so.12.0.4
pdcpy.libs/libpdc-e9878dca.so.0.6.0
pdcpy.libs/libpdc_commons-5f5fdea8.so
pdcpy-0.0.16.dist-info/METADATA
pdcpy-0.0.16.dist-info/WHEEL
pdcpy-0.0.16.dist-info/top_level.txt
pdcpy-0.0.16.dist-info/RECORD
