Metadata-Version: 2.4
Name: PDCpy
Version: 0.0.16
Summary: PDCpy is the official Python interface for PDC.
Author-email: Craig White <gerzytet@gmail.com>, Houjun Tang <htang4@lbl.gov>
Classifier: Programming Language :: Python :: 3
Classifier: Operating System :: Unix
Requires-Python: >=3.7
